README.md
setup.py
bitpanda_secp256k1_hd_utils.egg-info/PKG-INFO
bitpanda_secp256k1_hd_utils.egg-info/SOURCES.txt
bitpanda_secp256k1_hd_utils.egg-info/dependency_links.txt
bitpanda_secp256k1_hd_utils.egg-info/requires.txt
bitpanda_secp256k1_hd_utils.egg-info/top_level.txt
bphdutils/__init__.py
bphdutils/hd.py